numfu/__init__.py
numfu/_version.py
numfu/ast_types.py
numfu/builtins.py
numfu/classes.py
numfu/cli.py
numfu/errors.py
numfu/interpreter.py
numfu/modules.py
numfu/parser.py
numfu/reconstruct.py
numfu/repl.py
numfu/typechecks.py
numfu/grammar/grammar.py
numfu/grammar/numfu.lark
numfu/stdlib/builtins.nfut
numfu_lang-0.2.0.dist-info/licenses/LICENSE
numfu_lang-0.2.0.dist-info/METADATA
numfu_lang-0.2.0.dist-info/WHEEL
numfu_lang-0.2.0.dist-info/entry_points.txt
numfu_lang-0.2.0.dist-info/top_level.txt
numfu_lang-0.2.0.dist-info/RECORD
