Metadata-Version: 2.4
Name: numfu-lang
Version: 0.2.0
Summary: The NumFu programming language
Author-email: Raphael <hello@alpharee.de>
License:                                 Apache License
Project-URL: Homepage, https://rphle.github.io/numfu
Project-URL: Documentation, https://rphle.github.io/numfu/docs
Project-URL: Source, https://github.com/rphle/numfu
Project-URL: Issues, https://github.com/rphle/numfu/issues
Keywords: programming language,math,functional,interpreter,numfu,educational,education,programming,language
Classifier: Development Status :: 4 - Beta
Classifier: Intended Audience :: Developers
Classifier: Topic :: Software Development :: Interpreters
Classifier: Topic :: Scientific/Engineering :: Mathematics
Classifier: License :: OSI Approved :: Apache Software License
Classifier: Programming Language :: Python :: 3
Classifier: Programming Language :: Python :: 3.10
Classifier: Programming Language :: Python :: 3.11
Classifier: Programming Language :: Python :: 3.12
Classifier: Programming Language :: Python :: 3.13
Requires-Python: >=3.10
License-File: LICENSE
Requires-Dist: click==8.2.1
Requires-Dist: lark==1.2.2
Requires-Dist: prompt_toolkit==3.0.51
Requires-Dist: rich==14.0.0
Requires-Dist: mpmath==1.3.0
Dynamic: license-file
